statsd_asgi/__init__.py
statsd_asgi/_middlewares/__init__.py
statsd_asgi/_middlewares/status_code.py
statsd_asgi/_middlewares/timing.py
statsd_asgi/_utils/__init__.py
statsd_asgi-0.1.0b1.dist-info/LICENSE
statsd_asgi-0.1.0b1.dist-info/METADATA
statsd_asgi-0.1.0b1.dist-info/WHEEL
statsd_asgi-0.1.0b1.dist-info/top_level.txt
statsd_asgi-0.1.0b1.dist-info/RECORD
