Metadata-Version: 2.1
Name: statsd-asgi
Version: 0.1.0b1
Summary: Export metrics about requests in your ASGI apps to statsd or Datadog
Home-page: https://github.com/andrewthetechie/statsd-asgi
Author: Andrew Herrington
Author-email: andrew.the.techie@gmail.com
License: MIT
Project-URL: Documentation, https://github.com/andrewthetechie/statsd-asgi
Project-URL: Source code, https://github.com/andrewthetechie/statsd-asgi
Project-URL: Issue tracker, https://github.com/andrewthetechie/statsd-asgi/issues
Keywords: asgi,statsd,datadog,starlette,fastapi
Platform: UNKNOWN
Classifier: Development Status :: 4 - Beta
Classifier: Intended Audience :: Developers
Classifier: License :: OSI Approved :: MIT License
Classifier: Programming Language :: Python
Classifier: Programming Language :: Python :: 3
Classifier: Programming Language :: Python :: 3.6
Classifier: Programming Language :: Python :: 3.7
Classifier: Programming Language :: Python :: 3.8
Classifier: Programming Language :: Python :: 3.9
Classifier: Framework :: AsyncIO
Requires-Python: >=3.6
Requires-Dist: datadog (>=0.41.0)
Provides-Extra: tests
Requires-Dist: pytest ; extra == 'tests'
Requires-Dist: pytest-cov ; extra == 'tests'
Requires-Dist: pytest-mock ; extra == 'tests'
